{
  "molt_type": "Instruction",
  "cantocore": "SNAP.TO=STACK; MERGE.SUPPORTS=PRIMARY+PHILOSOPHY+DIRECTIVE",
  "snap_config": {
    "stack_priority": 23,
    "supports_merge": true
  },
  "merge_logic": {
    "merge_as": "instruction",
    "accepts": [
      "Primary",
      "Blueprint",
      "Directive"
    ]
  },
  "ledger": {
    "originator": "Christopher L Haynes",
    "verified_by": "PoeUMG",
    "created_at": "AUTO",
    "edit_log": []
  },
  "display": {
    "color": "yellow",
    "icon": "📄"
  },
  "code_modules": [],
  "runtime_behavior_flags": {},
  "agent_orchestration": {},
  "integration_layer": {},
  "future_extensions": [],
  "block_id": "23c_feature_voting_public_idea_submission",
  "label": "Public Idea Submission",
  "category": "Web App Builder/Product Feedback Surveys Voting/23C Feature Voting",
  "description": "Users post ideas",
  "tags": [
    "public_idea_submission"
  ],
  "example_block_data": {
    "content": "Users post ideas"
  },
  "editable_fields": {
    "content": "Users post ideas"
  }
}