{
  "molt_type": "Instruction",
  "cantocore": "SNAP.TO=STACK; MERGE.SUPPORTS=PRIMARY+PHILOSOPHY+DIRECTIVE",
  "snap_config": {
    "stack_priority": 25,
    "supports_merge": true
  },
  "merge_logic": {
    "merge_as": "instruction",
    "accepts": [
      "Primary",
      "Blueprint",
      "Directive"
    ]
  },
  "ledger": {
    "originator": "Christopher L Haynes",
    "verified_by": "PoeUMG",
    "created_at": "AUTO",
    "edit_log": []
  },
  "display": {
    "color": "yellow",
    "icon": "📄"
  },
  "code_modules": [],
  "runtime_behavior_flags": {},
  "agent_orchestration": {},
  "integration_layer": {},
  "future_extensions": [],
  "block_id": "25b_inline_tooltips_walkthroughs_embedded_video_help_loom_youtube",
  "label": "Embedded Video Help (Loom, YouTube)",
  "category": "Web App Builder/Documentation Help Support/25B Inline Tooltips Walkthroughs",
  "description": "Multimedia onboarding",
  "tags": [
    "embedded_video_help_loom_youtube"
  ],
  "example_block_data": {
    "content": "Multimedia onboarding"
  },
  "editable_fields": {
    "content": "Multimedia onboarding"
  }
}