{
  "molt_type": "Instruction",
  "cantocore": "SNAP.TO=STACK; MERGE.SUPPORTS=PRIMARY+PHILOSOPHY+DIRECTIVE",
  "snap_config": {
    "stack_priority": 9,
    "supports_merge": true
  },
  "merge_logic": {
    "merge_as": "instruction",
    "accepts": [
      "Primary",
      "Blueprint",
      "Directive"
    ]
  },
  "ledger": {
    "originator": "Christopher L Haynes",
    "verified_by": "PoeUMG",
    "created_at": "AUTO",
    "edit_log": []
  },
  "display": {
    "color": "yellow",
    "icon": "📄"
  },
  "code_modules": [],
  "runtime_behavior_flags": {},
  "agent_orchestration": {},
  "integration_layer": {},
  "future_extensions": [],
  "block_id": "9c_risk_change_blockers_incident_report",
  "label": "Incident Report",
  "category": "Business Plans/Web App/Chatbot/9C Risk Change Blockers",
  "description": "System or team failure documentation and aftermath report",
  "tags": [
    "incident_report"
  ],
  "example_block_data": {
    "content": "System or team failure documentation and aftermath report"
  },
  "editable_fields": {
    "content": "System or team failure documentation and aftermath report"
  }
}