{
  "block_id": "facial_expression_model",
  "label": "Facial Expression Model",
  "category": "Voice & Avatar Extensions",
  "description": "Emotion layer on avatar",
  "molt_type": "Instruction",
  "tags": [
    "facial_expression_model",
    "chatbot",
    "modular"
  ],
  "cantocore": "SNAP.TO=STACK; MERGE.SUPPORTS=PRIMARY+PHILOSOPHY+DIRECTIVE",
  "snap_config": {
    "stack_priority": 2,
    "supports_merge": true
  },
  "merge_logic": {
    "merge_as": "instruction",
    "accepts": [
      "Primary",
      "Blueprint",
      "Directive"
    ]
  },
  "ledger": {
    "originator": "Christopher L Haynes",
    "verified_by": "PoeUMG",
    "created_at": "AUTO",
    "edit_log": []
  },
  "display": {
    "color": "yellow",
    "icon": "😊"
  },
  "code_modules": [],
  "runtime_behavior_flags": {},
  "agent_orchestration": {},
  "integration_layer": {},
  "future_extensions": [],
  "example_block_data": {
    "content": "Emotion layer on avatar This logic defines runtime or system-facing behavior accordingly."
  },
  "editable_fields": {
    "content": "Facial Expression Model: Emotion layer on avatar"
  }
}