{
  "block_id": "020_gdpr_ccpa_disclosure_file CATEGORY 4: INVESTOR DOCUMENTATION",
  "label": "020 Gdpr Ccpa Disclosure File Category 4: Investor Documentation",
  "category": "AUTO-GEN-SET3",
  "molt_type": "Subject",
  "description": "Auto-generated UMG block for 020_gdpr_ccpa_disclosure_file CATEGORY 4: INVESTOR DOCUMENTATION",
  "tags": [
    "autogen",
    "missing",
    "set3"
  ],
  "snap_config": {
    "snap_to": [],
    "accepts": [
      "Instruction",
      "Directive",
      "Philosophy",
      "Blueprint"
    ],
    "order": 0,
    "priority": 1,
    "scope": "local",
    "locked": false
  },
  "display": {
    "color": "green",
    "icon": "🧱"
  },
  "editable_fields": [],
  "code_modules": [],
  "cantocore": "AUTO.FILL.CANTOCODE",
  "merge_behavior": {
    "merge_as": "default",
    "merge_strategy": "layered_if_non_conflict",
    "priority": 0,
    "conflict_resolution": "last_write_wins",
    "overrides": [],
    "merge_origin": "AUTO"
  },
  "domain": "",
  "subcategory": "General"
}