{
  "molt_type": "Instruction",
  "cantocore": "SNAP.TO=STACK; MERGE.SUPPORTS=PRIMARY+PHILOSOPHY+DIRECTIVE",
  "snap_config": {
    "snap_to": [],
    "accepts": [
      "Blueprint",
      "Directive",
      "Philosophy"
    ],
    "order": 0,
    "priority": 2,
    "scope": "local",
    "locked": false,
    "stack_priority": 18,
    "supports_merge": true
  },
  "display": {
    "color": "yellow",
    "icon": "📄"
  },
  "code_modules": [],
  "block_id": "18f_custom_fields_ux_patterns_form_as_wizard_dialogue",
  "label": "Form as Wizard / Dialogue",
  "category": "Web App Builder/Forms Validation Input/18F Custom Fields Ux Patterns",
  "description": "Progressive disclosure",
  "tags": [
    "form_as_wizard_dialogue"
  ],
  "editable_fields": {
    "content": "Progressive disclosure"
  },
  "merge_behavior": {
    "merge_as": "default",
    "merge_strategy": "layered_if_non_conflict",
    "priority": 0,
    "conflict_resolution": "last_write_wins",
    "overrides": [],
    "merge_origin": "AUTO"
  },
  "domain": "",
  "subcategory": "General"
}