{
  "block_id": "blueprint_block_preview_card",
  "label": "Card layout preview",
  "category": "system_blueprint",
  "molt_type": "Blueprint",
  "tags": [
    "autogen",
    "core_logic"
  ],
  "description": "Card layout preview",
  "editable_fields": [],
  "snap_config": {
    "snap_to": "stack",
    "accepts": [],
    "order": 0,
    "priority": 5,
    "scope": "local",
    "locked": false
  },
  "cantocore": {
    "summary": "Card layout preview"
  },
  "display": {
    "color": "Blueprint",
    "icon": "circle"
  },
  "merge_behavior": {
    "merge_as": "default",
    "merge_strategy": "layered_if_non_conflict",
    "priority": 0,
    "conflict_resolution": "last_write_wins",
    "overrides": [],
    "merge_origin": "AUTO"
  },
  "domain": "",
  "subcategory": "General",
  "code_modules": []
}